djangokit/cli/__init__.py
djangokit/cli/__main__.py
djangokit/cli/app.py
djangokit/cli/base.py
djangokit/cli/build.py
djangokit/cli/django.py
djangokit/cli/routes/README
djangokit/cli/routes/__init__.py
djangokit/cli/scaffolding/__init__.py
djangokit/cli/scaffolding/project.py
djangokit/cli/scaffolding/routes.py
djangokit/cli/settings.standalone.toml
djangokit/cli/state.py
djangokit/cli/utils/__init__.py
djangokit/cli/utils/console.py
djangokit/cli/utils/const.py
djangokit/cli/utils/params.py
djangokit/cli/utils/project.py
djangokit/cli/utils/run.py
djangokit/cli/utils/settings.py
org_djangokit_cli-0.0.7.dist-info/LICENSE
org_djangokit_cli-0.0.7.dist-info/WHEEL
org_djangokit_cli-0.0.7.dist-info/entry_points.txt
org_djangokit_cli-0.0.7.dist-info/METADATA
org_djangokit_cli-0.0.7.dist-info/RECORD
