Metadata-Version: 2.1
Name: org-djangokit-cli
Version: 0.0.7
Summary: DjangoKit command line interface
License: MIT
Author: Wyatt Baldwin
Author-email: self@wyattbaldwin.com
Requires-Python: >=3.8,<4.0
Classifier: License :: OSI Approved :: MIT License
Classifier: Programming Language :: Python :: 3
Classifier: Programming Language :: Python :: 3.8
Classifier: Programming Language :: Python :: 3.9
Classifier: Programming Language :: Python :: 3.10
Classifier: Programming Language :: Python :: 3.11
Requires-Dist: cookiecutter (>=2.1.1,<3.0.0)
Requires-Dist: org-djangokit-core (>=0.0.3.dev0)
Requires-Dist: typer[all] (>=0.7.0)
Requires-Dist: types-toml (>=0.10.8.1,<0.11.0.0)
Requires-Dist: watchdog (>=2.0)
